syn/cells_sim.v
// Behavioural simulation models for demo130 standard cells
`timescale 1ns/1ps

module INV  (input A, output Y); assign #0.08 Y = ~A; endmodule
module BUF  (input A, output Y); assign #0.10 Y =  A; endmodule
module NAND2(input A, B, output Y); assign #0.10 Y = ~(A & B); endmodule
module NOR2 (input A, B, output Y); assign #0.12 Y = ~(A | B); endmodule
module AND2 (input A, B, output Y); assign #0.13 Y =  A & B;  endmodule
module OR2  (input A, B, output Y); assign #0.14 Y =  A | B;  endmodule
module XOR2 (input A, B, output Y); assign #0.18 Y =  A ^ B;  endmodule
module XNOR2(input A, B, output Y); assign #0.18 Y = ~(A ^ B); endmodule
module MUX2 (input A, B, S, output Y); assign #0.15 Y = S ? B : A; endmodule

module DFF (
    input      CLK,
    input      D,
    output reg Q,
    output     QN
);
    assign QN = ~Q;
    always @(posedge CLK) Q <= D;
endmodule

syn/netlist.v
/* Generated by Yosys 0.33 (git sha1 2584903a060) */

module acc4(clk, rst_n, en, a, acc, carry);
  wire _00_;
  wire _01_;
  wire _02_;
  wire _03_;
  wire _04_;
  wire _05_;
  wire _06_;
  wire _07_;
  wire _08_;
  wire _09_;
  wire _10_;
  wire _11_;
  wire _12_;
  wire _13_;
  wire _14_;
  wire _15_;
  wire _16_;
  wire _17_;
  wire _18_;
  wire _19_;
  wire _20_;
  wire _21_;
  wire _22_;
  wire _23_;
  wire _24_;
  wire _25_;
  wire _26_;
  wire _27_;
  wire _28_;
  wire _29_;
  wire _30_;
  wire _31_;
  wire _32_;
  wire _33_;
  wire _34_;
  wire _35_;
  wire _36_;
  wire _37_;
  wire _38_;
  wire _39_;
  wire _40_;
  wire _41_;
  wire _42_;
  wire _43_;
  input [3:0] a;
  wire [3:0] a;
  output [3:0] acc;
  wire [3:0] acc;
  output carry;
  wire carry;
  input clk;
  wire clk;
  input en;
  wire en;
  input rst_n;
  wire rst_n;
  INV _44_ (
    .A(acc[3]),
    .Y(_05_)
  );
  INV _45_ (
    .A(rst_n),
    .Y(_06_)
  );
  AND2 _46_ (
    .A(en),
    .B(a[0]),
    .Y(_07_)
  );
  NAND2 _47_ (
    .A(acc[0]),
    .B(_07_),
    .Y(_08_)
  );
  NOR2 _48_ (
    .A(acc[0]),
    .B(_07_),
    .Y(_09_)
  );
  NAND2 _49_ (
    .A(rst_n),
    .B(_08_),
    .Y(_10_)
  );
  NOR2 _50_ (
    .A(_09_),
    .B(_10_),
    .Y(_00_)
  );
  AND2 _51_ (
    .A(acc[0]),
    .B(a[0]),
    .Y(_11_)
  );
  NAND2 _52_ (
    .A(acc[1]),
    .B(a[1]),
    .Y(_12_)
  );
  XOR2 _53_ (
    .A(acc[1]),
    .B(a[1]),
    .Y(_13_)
  );
  NAND2 _54_ (
    .A(_11_),
    .B(_13_),
    .Y(_14_)
  );
  XNOR2 _55_ (
    .A(_11_),
    .B(_13_),
    .Y(_15_)
  );
  NAND2 _56_ (
    .A(en),
    .B(_15_),
    .Y(_16_)
  );
  NOR2 _57_ (
    .A(en),
    .B(acc[1]),
    .Y(_17_)
  );
  NOR2 _58_ (
    .A(_06_),
    .B(_17_),
    .Y(_18_)
  );
  AND2 _59_ (
    .A(_16_),
    .B(_18_),
    .Y(_01_)
  );
  AND2 _60_ (
    .A(_12_),
    .B(_14_),
    .Y(_19_)
  );
  NAND2 _61_ (
    .A(acc[2]),
    .B(a[2]),
    .Y(_20_)
  );
  XNOR2 _62_ (
    .A(acc[2]),
    .B(a[2]),
    .Y(_21_)
  );
  OR2 _63_ (
    .A(_19_),
    .B(_21_),
    .Y(_22_)
  );
  XNOR2 _64_ (
    .A(_19_),
    .B(_21_),
    .Y(_23_)
  );
  NAND2 _65_ (
    .A(en),
    .B(_23_),
    .Y(_24_)
  );
  NOR2 _66_ (
    .A(en),
    .B(acc[2]),
    .Y(_25_)
  );
  NOR2 _67_ (
    .A(_06_),
    .B(_25_),
    .Y(_26_)
  );
  AND2 _68_ (
    .A(_24_),
    .B(_26_),
    .Y(_02_)
  );
  NOR2 _69_ (
    .A(en),
    .B(_05_),
    .Y(_27_)
  );
  NAND2 _70_ (
    .A(_20_),
    .B(_22_),
    .Y(_28_)
  );
  AND2 _71_ (
    .A(acc[3]),
    .B(a[3]),
    .Y(_29_)
  );
  XOR2 _72_ (
    .A(acc[3]),
    .B(a[3]),
    .Y(_30_)
  );
  NOR2 _73_ (
    .A(_28_),
    .B(_30_),
    .Y(_31_)
  );
  NAND2 _74_ (
    .A(_28_),
    .B(_30_),
    .Y(_32_)
  );
  NAND2 _75_ (
    .A(en),
    .B(_32_),
    .Y(_33_)
  );
  NOR2 _76_ (
    .A(_31_),
    .B(_33_),
    .Y(_34_)
  );
  NOR2 _77_ (
    .A(_27_),
    .B(_34_),
    .Y(_35_)
  );
  NOR2 _78_ (
    .A(_06_),
    .B(_35_),
    .Y(_03_)
  );
  NOR2 _79_ (
    .A(_29_),
    .B(_33_),
    .Y(_36_)
  );
  OR2 _80_ (
    .A(carry),
    .B(en),
    .Y(_37_)
  );
  NAND2 _81_ (
    .A(rst_n),
    .B(_37_),
    .Y(_38_)
  );
  NOR2 _82_ (
    .A(_36_),
    .B(_38_),
    .Y(_04_)
  );
  DFF _83_ (
    .CLK(clk),
    .D(_00_),
    .Q(acc[0]),
    .QN(_39_)
  );
  DFF _84_ (
    .CLK(clk),
    .D(_01_),
    .Q(acc[1]),
    .QN(_43_)
  );
  DFF _85_ (
    .CLK(clk),
    .D(_02_),
    .Q(acc[2]),
    .QN(_42_)
  );
  DFF _86_ (
    .CLK(clk),
    .D(_03_),
    .Q(acc[3]),
    .QN(_41_)
  );
  DFF _87_ (
    .CLK(clk),
    .D(_04_),
    .Q(carry),
    .QN(_40_)
  );
endmodule

rtl/tb_acc4.v
`timescale 1ns/1ps
module tb_acc4;
    reg        clk, rst_n, en;
    reg  [3:0] a;
    wire [3:0] acc;
    wire       carry;

    acc4 dut (.*);

    // 10 ns clock
    initial clk = 0;
    always #5 clk = ~clk;

    // Reference model
    reg  [4:0] ref_acc;
    integer    errors = 0;

    task check;
        input [3:0] exp_acc;
        input       exp_carry;
        input [63:0] label;
        begin
            #1; // small delta after rising edge
            if (acc !== exp_acc || carry !== exp_carry) begin
                $display("FAIL [%0d]: acc=%b carry=%b  exp acc=%b carry=%b",
                         label, acc, carry, exp_acc, exp_carry);
                errors = errors + 1;
            end else begin
                $display("PASS [%0d]: acc=%0d carry=%0d", label, acc, carry);
            end
        end
    endtask

    integer i;
    initial begin
        $dumpfile("sim/rtl_sim.vcd");
        $dumpvars(0, tb_acc4);

        rst_n = 0; en = 0; a = 0;
        @(posedge clk); @(posedge clk);

        // Release reset
        rst_n = 1;
        check(0, 0, 1);

        // Accumulate 3 three times: 3, 6, 9 (carry=0)
        en = 1; a = 4'd3;
        @(posedge clk); check(4'd3,  0, 2);
        @(posedge clk); check(4'd6,  0, 3);
        @(posedge clk); check(4'd9,  0, 4);

        // Accumulate 10: 9+10=19 => acc=3, carry=1
        a = 4'd10;
        @(posedge clk); check(4'd3, 1, 5);

        // Accumulate 4: 3+4=7, carry clears
        a = 4'd4;
        @(posedge clk); check(4'd7, 0, 6);

        // en=0: value held
        en = 0;
        @(posedge clk); check(4'd7, 0, 7);

        // Synchronous reset while running
        en = 1; a = 4'd15;
        @(posedge clk); // 7+15=22 => acc=6,carry=1
        rst_n = 0;
        @(posedge clk); check(4'd0, 0, 8);
        rst_n = 1;

        // All-ones: 15+15=30 => acc=14,carry=1
        a = 4'd15;
        @(posedge clk); check(4'd15, 0, 9);
        @(posedge clk); check(4'd14, 1, 10);

        if (errors == 0)
            $display("\n=== RTL SIM PASSED (%0d checks) ===", 10);
        else
            $display("\n=== RTL SIM FAILED (%0d errors) ===", errors);

        $finish;
    end
endmodule

sim/rtl_sim.vcd
$date
	Thu May 21 05:00:42 2026
$end
$version
	Icarus Verilog
$end
$timescale
	1ps
$end
$scope module tb_acc4 $end
$var wire 1 ! carry $end
$var wire 4 " acc [3:0] $end
$var reg 4 # a [3:0] $end
$var reg 1 $ clk $end
$var reg 1 % en $end
$var reg 1 & rst_n $end
$var integer 32 ' errors [31:0] $end
$scope module dut $end
$var wire 4 ( a [3:0] $end
$var wire 1 $ clk $end
$var wire 1 % en $end
$var wire 1 & rst_n $end
$var wire 1 ! carry $end
$var wire 4 ) acc [3:0] $end
$var wire 1 * _43_ $end
$var wire 1 + _42_ $end
$var wire 1 , _41_ $end
$var wire 1 - _40_ $end
$var wire 1 . _39_ $end
$var wire 1 / _38_ $end
$var wire 1 0 _37_ $end
$var wire 1 1 _36_ $end
$var wire 1 2 _35_ $end
$var wire 1 3 _34_ $end
$var wire 1 4 _33_ $end
$var wire 1 5 _32_ $end
$var wire 1 6 _31_ $end
$var wire 1 7 _30_ $end
$var wire 1 8 _29_ $end
$var wire 1 9 _28_ $end
$var wire 1 : _27_ $end
$var wire 1 ; _26_ $end
$var wire 1 < _25_ $end
$var wire 1 = _24_ $end
$var wire 1 > _23_ $end
$var wire 1 ? _22_ $end
$var wire 1 @ _21_ $end
$var wire 1 A _20_ $end
$var wire 1 B _19_ $end
$var wire 1 C _18_ $end
$var wire 1 D _17_ $end
$var wire 1 E _16_ $end
$var wire 1 F _15_ $end
$var wire 1 G _14_ $end
$var wire 1 H _13_ $end
$var wire 1 I _12_ $end
$var wire 1 J _11_ $end
$var wire 1 K _10_ $end
$var wire 1 L _09_ $end
$var wire 1 M _08_ $end
$var wire 1 N _07_ $end
$var wire 1 O _06_ $end
$var wire 1 P _05_ $end
$var wire 1 Q _04_ $end
$var wire 1 R _03_ $end
$var wire 1 S _02_ $end
$var wire 1 T _01_ $end
$var wire 1 U _00_ $end
$scope module _44_ $end
$var wire 1 V A $end
$var wire 1 P Y $end
$upscope $end
$scope module _45_ $end
$var wire 1 & A $end
$var wire 1 O Y $end
$upscope $end
$scope module _46_ $end
$var wire 1 % A $end
$var wire 1 W B $end
$var wire 1 N Y $end
$upscope $end
$scope module _47_ $end
$var wire 1 X A $end
$var wire 1 N B $end
$var wire 1 M Y $end
$upscope $end
$scope module _48_ $end
$var wire 1 Y A $end
$var wire 1 N B $end
$var wire 1 L Y $end
$upscope $end
$scope module _49_ $end
$var wire 1 & A $end
$var wire 1 M B $end
$var wire 1 K Y $end
$upscope $end
$scope module _50_ $end
$var wire 1 L A $end
$var wire 1 K B $end
$var wire 1 U Y $end
$upscope $end
$scope module _51_ $end
$var wire 1 Z A $end
$var wire 1 [ B $end
$var wire 1 J Y $end
$upscope $end
$scope module _52_ $end
$var wire 1 \ A $end
$var wire 1 ] B $end
$var wire 1 I Y $end
$upscope $end
$scope module _53_ $end
$var wire 1 ^ A $end
$var wire 1 _ B $end
$var wire 1 H Y $end
$upscope $end
$scope module _54_ $end
$var wire 1 J A $end
$var wire 1 H B $end
$var wire 1 G Y $end
$upscope $end
$scope module _55_ $end
$var wire 1 J A $end
$var wire 1 H B $end
$var wire 1 F Y $end
$upscope $end
$scope module _56_ $end
$var wire 1 % A $end
$var wire 1 F B $end
$var wire 1 E Y $end
$upscope $end
$scope module _57_ $end
$var wire 1 % A $end
$var wire 1 ` B $end
$var wire 1 D Y $end
$upscope $end
$scope module _58_ $end
$var wire 1 O A $end
$var wire 1 D B $end
$var wire 1 C Y $end
$upscope $end
$scope module _59_ $end
$var wire 1 E A $end
$var wire 1 C B $end
$var wire 1 T Y $end
$upscope $end
$scope module _60_ $end
$var wire 1 I A $end
$var wire 1 G B $end
$var wire 1 B Y $end
$upscope $end
$scope module _61_ $end
$var wire 1 a A $end
$var wire 1 b B $end
$var wire 1 A Y $end
$upscope $end
$scope module _62_ $end
$var wire 1 c A $end
$var wire 1 d B $end
$var wire 1 @ Y $end
$upscope $end
$scope module _63_ $end
$var wire 1 B A $end
$var wire 1 @ B $end
$var wire 1 ? Y $end
$upscope $end
$scope module _64_ $end
$var wire 1 B A $end
$var wire 1 @ B $end
$var wire 1 > Y $end
$upscope $end
$scope module _65_ $end
$var wire 1 % A $end
$var wire 1 > B $end
$var wire 1 = Y $end
$upscope $end
$scope module _66_ $end
$var wire 1 % A $end
$var wire 1 e B $end
$var wire 1 < Y $end
$upscope $end
$scope module _67_ $end
$var wire 1 O A $end
$var wire 1 < B $end
$var wire 1 ; Y $end
$upscope $end
$scope module _68_ $end
$var wire 1 = A $end
$var wire 1 ; B $end
$var wire 1 S Y $end
$upscope $end
$scope module _69_ $end
$var wire 1 % A $end
$var wire 1 P B $end
$var wire 1 : Y $end
$upscope $end
$scope module _70_ $end
$var wire 1 A A $end
$var wire 1 ? B $end
$var wire 1 9 Y $end
$upscope $end
$scope module _71_ $end
$var wire 1 f A $end
$var wire 1 g B $end
$var wire 1 8 Y $end
$upscope $end
$scope module _72_ $end
$var wire 1 h A $end
$var wire 1 i B $end
$var wire 1 7 Y $end
$upscope $end
$scope module _73_ $end
$var wire 1 9 A $end
$var wire 1 7 B $end
$var wire 1 6 Y $end
$upscope $end
$scope module _74_ $end
$var wire 1 9 A $end
$var wire 1 7 B $end
$var wire 1 5 Y $end
$upscope $end
$scope module _75_ $end
$var wire 1 % A $end
$var wire 1 5 B $end
$var wire 1 4 Y $end
$upscope $end
$scope module _76_ $end
$var wire 1 6 A $end
$var wire 1 4 B $end
$var wire 1 3 Y $end
$upscope $end
$scope module _77_ $end
$var wire 1 : A $end
$var wire 1 3 B $end
$var wire 1 2 Y $end
$upscope $end
$scope module _78_ $end
$var wire 1 O A $end
$var wire 1 2 B $end
$var wire 1 R Y $end
$upscope $end
$scope module _79_ $end
$var wire 1 8 A $end
$var wire 1 4 B $end
$var wire 1 1 Y $end
$upscope $end
$scope module _80_ $end
$var wire 1 % B $end
$var wire 1 0 Y $end
$var wire 1 ! A $end
$upscope $end
$scope module _81_ $end
$var wire 1 & A $end
$var wire 1 0 B $end
$var wire 1 / Y $end
$upscope $end
$scope module _82_ $end
$var wire 1 1 A $end
$var wire 1 / B $end
$var wire 1 Q Y $end
$upscope $end
$scope module _83_ $end
$var wire 1 $ CLK $end
$var wire 1 U D $end
$var wire 1 . QN $end
$var reg 1 j Q $end
$upscope $end
$scope module _84_ $end
$var wire 1 $ CLK $end
$var wire 1 T D $end
$var wire 1 * QN $end
$var reg 1 k Q $end
$upscope $end
$scope module _85_ $end
$var wire 1 $ CLK $end
$var wire 1 S D $end
$var wire 1 + QN $end
$var reg 1 l Q $end
$upscope $end
$scope module _86_ $end
$var wire 1 $ CLK $end
$var wire 1 R D $end
$var wire 1 , QN $end
$var reg 1 m Q $end
$upscope $end
$scope module _87_ $end
$var wire 1 $ CLK $end
$var wire 1 Q D $end
$var wire 1 - QN $end
$var reg 1 ! Q $end
$upscope $end
$upscope $end
$scope task check $end
$var reg 4 n exp_acc [3:0] $end
$var reg 1 o exp_carry $end
$var reg 64 p label [63:0] $end
$upscope $end
$upscope $end
$enddefinitions $end
$comment Show the parameter values. $end
$dumpall
$end
#0
$dumpvars
bx p
xo
bx n
xm
xl
xk
xj
0i
xh
0g
xf
xe
0d
xc
0b
xa
x`
0_
x^
0]
x\
0[
xZ
xY
xX
0W
xV
xU
xT
xS
xR
xQ
xP
xO
xN
xM
xL
xK
xJ
xI
xH
xG
xF
xE
xD
xC
xB
xA
x@
x?
x>
x=
x<
x;
x:
x9
x8
x7
x6
x5
x4
x3
x2
x1
x0
x/
x.
x-
x,
x+
x*
bx )
b0 (
b0 '
0&
0%
0$
b0 #
bx "
x!
$end
#80
1O
#100
1I
1A
1/
14
1=
1E
1K
#130
0J
08
0N
#200
0C
0;
0R
#220
0Q
03
01
0U
#230
1G
1M
#330
0T
0S
#360
1B
#500
1?
#600
09
#700
15
#5000
1.
0Z
0Y
0X
1*
0`
0^
0\
1+
0e
0c
0a
1,
0h
0f
0V
1-
0j
0k
0l
b0 "
b0 )
0m
0!
1$
#5080
1P
#5120
1L
1D
1<
#5140
00
#5180
1@
0H
07
#5200
0:
#5300
16
#5320
12
#5360
1>
1F
#10000
0$
#15000
b1 p
0o
b0 n
1&
1$
#15080
0O
#15100
0K
#16000
1W
1[
1]
1_
b11 #
b11 (
1%
#16100
0E
0=
04
#16120
0D
0<
#16130
1N
#16140
10
#16180
1H
#16220
11
#16240
0/
1C
1;
#16250
0L
#16360
0F
#16370
1U
#16460
1E
#16590
1T
#20000
0$
#25000
0.
1Z
1Y
1X
0*
1`
1^
1\
1j
b11 "
b11 )
1k
b10 p
b11 n
1$
#25100
0M
0I
#25130
1J
#25180
0H
#25200
1K
#25230
0B
#25320
0U
#25410
0>
#25510
1=
#25640
1S
#30000
0$
#35000
0+
1e
1c
1a
1.
0Z
0Y
0X
1l
b110 "
b110 )
0j
b11 p
b110 n
1$
#35100
1M
#35130
0J
#35180
0@
#35200
0K
#35310
1F
#35320
1U
0?
#35360
1>
#35410
0E
#35420
19
#35460
0=
#35540
06
0T
#35590
0S
#35660
13
#35780
02
#35900
1R
#40000
0$
#45000
0.
1Z
1Y
1X
1*
0`
0^
0\
1+
0e
0c
0a
0,
1h
1f
1V
1j
0k
0l
b1001 "
b1001 )
1m
b100 p
b1001 n
1$
#45080
0P
#45100
0M
1I
#45130
1J
#45180
1@
1H
17
#45200
1K
#45230
1B
#45280
0G
05
#45320
0U
1?
#45380
14
#45410
0B
#45420
09
#45500
03
01
#45520
15
#45590
0>
#45620
04
12
1Q
#45690
1=
#45740
13
11
0R
#45820
1S
#45860
02
0Q
#45980
1R
#46000
0W
0[
1g
1i
b1010 #
b1010 (
#46130
0N
0J
18
#46180
07
#46230
1M
1G
#46250
01
#46300
16
#46310
0F
#46330
0K
#46360
1B
#46370
1Q
#46410
1E
#46420
03
#46450
1U
#46540
12
1T
1>
#46640
0=
#46660
0R
#46770
0S
#50000
0$
#55000
0-
1,
0h
0f
0V
0*
1`
1^
1\
1!
0m
b11 "
b11 )
1k
b101 p
1o
b11 n
1$
#55080
1P
#55100
0I
#55130
08
#55180
17
0H
#55230
0B
#55250
11
#55300
06
#55360
1F
#55370
0Q
#55410
0>
#55420
13
#55460
0E
#55510
1=
#55540
02
#55590
0T
#55640
1S
#55660
1R
#56000
0]
0_
1b
1d
0g
0i
b100 #
b100 (
#56100
1I
#56180
0@
1H
07
#56230
1B
#56300
16
#56360
0F
#56420
03
#56460
1E
#56540
12
#56590
1T
#56660
0R
#60000
0$
#65000
0+
1e
1c
1a
1-
b111 "
b111 )
1l
0!
b110 p
0o
b111 n
1$
#65100
0A
#65180
1@
#65200
19
#65320
06
#65360
1>
#65440
13
#65460
0=
#65560
02
#65590
0S
#65680
1R
#66000
0%
#66100
1=
14
#66140
00
#66220
03
01
#66230
1S
#66240
1/
#66340
12
#66460
0R
#70000
0$
#75000
b111 p
1$
#76000
1W
1[
1]
1_
1g
1i
b1111 #
b1111 (
1%
#76100
0I
0=
04
#76130
1N
1J
#76140
10
#76180
0H
17
#76220
13
11
#76230
0M
0B
0S
#76240
0/
#76280
05
#76330
1K
#76340
02
#76380
14
#76410
0>
#76450
0U
#76460
1R
#76500
03
01
#76510
1=
#76620
12
1Q
#76640
1S
#76740
0R
#80000
0$
#85000
1.
0Z
0Y
0X
0-
b110 "
b110 )
0j
1!
0&
1$
#85080
1O
#85100
1M
1/
#85130
0J
#85200
0C
0;
#85220
0Q
#85310
1F
#85330
0T
0S
#85410
0E
#90000
0$
#95000
1-
1+
0e
0c
0a
1*
0`
0^
0\
0!
0l
b0 "
b0 )
0k
b1000 p
b0 n
1$
#95100
1A
1I
#95180
0@
1H
#95200
09
#95230
1B
#95300
15
#95360
0F
#95400
04
#95460
1E
#95520
13
11
#95640
02
#96000
1&
#96080
0O
#96100
0K
0/
#96200
1C
1;
1R
#96220
1U
#96330
1T
1S
#100000
0$
#105000
0.
1Z
1Y
1X
0*
1`
1^
1\
0+
1e
1c
1a
0,
1h
1f
1V
1j
1k
1l
b1111 "
b1111 )
1m
b1001 p
b1111 n
1$
#105080
0P
#105100
0M
0I
0A
#105130
1J
18
#105180
1@
0H
07
#105200
1K
19
#105230
0B
#105250
01
#105320
0U
#105370
1Q
#110000
0$
#115000
0-
1.
0Z
0Y
0X
1!
b1110 "
b1110 )
0j
b1010 p
1o
b1110 n
1$
#115100
1M
#115130
0J
#115200
0K
#115310
1F
#115320
1U
#115410
0E
#115540
0T
