rtl/rv32i/rv32i_alu.v
// RV32I ALU
module rv32i_alu (
    input  [31:0] a,
    input  [31:0] b,
    input  [3:0]  op,
    output reg [31:0] result,
    output        zero
);
    localparam ADD  = 4'd0, SUB  = 4'd1, SLL  = 4'd2, SLT  = 4'd3,
               SLTU = 4'd4, XOR  = 4'd5, SRL  = 4'd6, SRA  = 4'd7,
               OR   = 4'd8, AND  = 4'd9, PASS = 4'd10;

    assign zero = (result == 32'd0);

    always @(*) begin
        case (op)
            ADD:  result = a + b;
            SUB:  result = a - b;
            SLL:  result = a << b[4:0];
            SLT:  result = ($signed(a) < $signed(b)) ? 32'd1 : 32'd0;
            SLTU: result = (a < b) ? 32'd1 : 32'd0;
            XOR:  result = a ^ b;
            SRL:  result = a >> b[4:0];
            SRA:  result = $signed(a) >>> b[4:0];
            OR:   result = a | b;
            AND:  result = a & b;
            PASS: result = b;
            default: result = a + b;
        endcase
    end
endmodule

rtl/rv32i/rv32i_regfile.v
// RV32I 32x32 register file (x0 hardwired to 0)
module rv32i_regfile (
    input         clk,
    input  [4:0]  rs1, rs2, rd,
    input  [31:0] wdata,
    input         wen,
    output [31:0] rdata1,
    output [31:0] rdata2
);
    reg [31:0] rf [1:31];

    assign rdata1 = (rs1 == 5'd0) ? 32'd0 : rf[rs1];
    assign rdata2 = (rs2 == 5'd0) ? 32'd0 : rf[rs2];

    always @(posedge clk)
        if (wen && rd != 5'd0) rf[rd] <= wdata;
endmodule

rtl/rv32i/rv32i_core.v
// RV32I Single-Cycle Core
// Interfaces with external IMEM and DMEM (not synthesized here)
module rv32i_core (
    input         clk,
    input         rst_n,
    // Instruction memory (read-only)
    output [31:0] imem_addr,
    input  [31:0] imem_rdata,
    // Data memory
    output [31:0] dmem_addr,
    output [31:0] dmem_wdata,
    output [3:0]  dmem_wmask,
    output        dmem_wen,
    input  [31:0] dmem_rdata
);
    // ── Opcode constants ────────────────────────────────────
    localparam OP_LUI   = 7'h37, OP_AUIPC = 7'h17,
               OP_JAL   = 7'h6F, OP_JALR  = 7'h67,
               OP_BRANCH= 7'h63, OP_LOAD  = 7'h03,
               OP_STORE = 7'h23, OP_ALUI  = 7'h13,
               OP_ALU   = 7'h33;

    // ── ALU op encoding ─────────────────────────────────────
    localparam ALU_ADD=4'd0, ALU_SUB=4'd1, ALU_SLL=4'd2, ALU_SLT=4'd3,
               ALU_SLTU=4'd4, ALU_XOR=4'd5, ALU_SRL=4'd6, ALU_SRA=4'd7,
               ALU_OR=4'd8,  ALU_AND=4'd9, ALU_PASS=4'd10;

    // ── PC ──────────────────────────────────────────────────
    reg  [31:0] pc;
    assign imem_addr = pc;

    // ── Instruction decode ───────────────────────────────────
    wire [31:0] instr  = imem_rdata;
    wire [6:0]  opcode = instr[6:0];
    wire [4:0]  rd     = instr[11:7];
    wire [2:0]  funct3 = instr[14:12];
    wire [4:0]  rs1    = instr[19:15];
    wire [4:0]  rs2    = instr[24:20];
    wire [6:0]  funct7 = instr[31:25];

    // Immediate generation
    wire [31:0] imm_i = {{20{instr[31]}}, instr[31:20]};
    wire [31:0] imm_s = {{20{instr[31]}}, instr[31:25], instr[11:7]};
    wire [31:0] imm_b = {{19{instr[31]}}, instr[31], instr[7],
                         instr[30:25], instr[11:8], 1'b0};
    wire [31:0] imm_u = {instr[31:12], 12'b0};
    wire [31:0] imm_j = {{11{instr[31]}}, instr[31], instr[19:12],
                         instr[20], instr[30:21], 1'b0};

    // ── Register file ────────────────────────────────────────
    wire [31:0] rf_rdata1, rf_rdata2;
    reg  [31:0] rf_wdata;
    reg         rf_wen;

    rv32i_regfile u_rf (
        .clk    (clk),
        .rs1    (rs1),   .rdata1 (rf_rdata1),
        .rs2    (rs2),   .rdata2 (rf_rdata2),
        .rd     (rd),    .wdata  (rf_wdata),  .wen (rf_wen)
    );

    // ── ALU ─────────────────────────────────────────────────
    reg  [31:0] alu_a, alu_b;
    reg  [3:0]  alu_op;
    wire [31:0] alu_result;
    wire        alu_zero;

    rv32i_alu u_alu (
        .a (alu_a), .b (alu_b), .op (alu_op),
        .result (alu_result), .zero (alu_zero)
    );

    // ── ALU input / op decode ────────────────────────────────
    wire is_r  = (opcode == OP_ALU);
    wire is_i  = (opcode == OP_ALUI);
    wire is_sub = is_r && funct7[5];
    wire is_sra = (funct3 == 3'b101) && funct7[5];

    always @(*) begin
        // ALU A: PC (for AUIPC/JAL/JALR) or rs1
        alu_a = (opcode == OP_AUIPC) ? pc : rf_rdata1;
        // ALU B: immediate or rs2
        alu_b = (is_r) ? rf_rdata2 :
                (opcode == OP_LUI || opcode == OP_AUIPC) ? imm_u :
                (opcode == OP_STORE) ? imm_s : imm_i;
        // ALU op decode
        case (funct3)
            3'b000: alu_op = (is_sub)  ? ALU_SUB : ALU_ADD;
            3'b001: alu_op = ALU_SLL;
            3'b010: alu_op = ALU_SLT;
            3'b011: alu_op = ALU_SLTU;
            3'b100: alu_op = ALU_XOR;
            3'b101: alu_op = is_sra   ? ALU_SRA : ALU_SRL;
            3'b110: alu_op = ALU_OR;
            3'b111: alu_op = ALU_AND;
            default: alu_op = ALU_ADD;
        endcase
        // Opcodes that always use ADD or PASS regardless of funct3
        if (opcode == OP_LUI)    alu_op = ALU_PASS;
        if (opcode == OP_AUIPC)  alu_op = ALU_ADD;
        if (opcode == OP_JAL)    alu_op = ALU_ADD;
        if (opcode == OP_JALR)   alu_op = ALU_ADD;
        if (opcode == OP_LOAD)   alu_op = ALU_ADD; // addr = base + imm_i
        if (opcode == OP_STORE)  alu_op = ALU_ADD; // addr = base + imm_s
        if (opcode == OP_BRANCH) alu_op = ALU_ADD; // comparisons done separately
    end

    // ── Branch condition ─────────────────────────────────────
    wire [31:0] rs1v = rf_rdata1, rs2v = rf_rdata2;
    wire        br_eq  = (rs1v == rs2v);
    wire        br_lt  = ($signed(rs1v) < $signed(rs2v));
    wire        br_ltu = (rs1v < rs2v);

    reg taken;
    always @(*) begin
        case (funct3)
            3'b000: taken = br_eq;
            3'b001: taken = !br_eq;
            3'b100: taken = br_lt;
            3'b101: taken = !br_lt;
            3'b110: taken = br_ltu;
            3'b111: taken = !br_ltu;
            default: taken = 1'b0;
        endcase
    end

    // ── Data memory ──────────────────────────────────────────
    assign dmem_addr  = alu_result;
    assign dmem_wdata = rs2v;
    assign dmem_wen   = (opcode == OP_STORE);

    // Byte-write mask from funct3
    assign dmem_wmask = (opcode == OP_STORE) ?
        (funct3 == 3'b000 ? (4'b0001 << alu_result[1:0]) :
         funct3 == 3'b001 ? (4'b0011 << {alu_result[1], 1'b0}) :
                             4'b1111) : 4'b0000;

    // Load data with sign/zero extension
    wire [31:0] lb  = {{24{dmem_rdata[7]}},  dmem_rdata[7:0]};
    wire [31:0] lbu = {24'd0,                 dmem_rdata[7:0]};
    wire [31:0] lh  = {{16{dmem_rdata[15]}}, dmem_rdata[15:0]};
    wire [31:0] lhu = {16'd0,                 dmem_rdata[15:0]};
    wire [31:0] lw  =                         dmem_rdata;

    reg [31:0] load_data;
    always @(*) begin
        case (funct3)
            3'b000: load_data = lb;
            3'b001: load_data = lh;
            3'b010: load_data = lw;
            3'b100: load_data = lbu;
            3'b101: load_data = lhu;
            default: load_data = lw;
        endcase
    end

    // ── Writeback ────────────────────────────────────────────
    wire [31:0] pc_plus4 = pc + 32'd4;

    always @(*) begin
        rf_wen   = 1'b0;
        rf_wdata = 32'd0;
        case (opcode)
            OP_ALU, OP_ALUI, OP_LUI, OP_AUIPC: begin
                rf_wen   = 1'b1;
                rf_wdata = alu_result;
            end
            OP_LOAD: begin
                rf_wen   = 1'b1;
                rf_wdata = load_data;
            end
            OP_JAL, OP_JALR: begin
                rf_wen   = 1'b1;
                rf_wdata = pc_plus4;
            end
            default: ;
        endcase
    end

    // ── Next PC ──────────────────────────────────────────────
    wire [31:0] pc_branch = pc + imm_b;
    wire [31:0] pc_jal    = pc + imm_j;
    wire [31:0] pc_jalr   = {alu_result[31:1], 1'b0};

    reg [31:0] next_pc;
    always @(*) begin
        case (opcode)
            OP_JAL:    next_pc = pc_jal;
            OP_JALR:   next_pc = pc_jalr;
            OP_BRANCH: next_pc = taken ? pc_branch : pc_plus4;
            default:   next_pc = pc_plus4;
        endcase
    end

    // ── PC register ──────────────────────────────────────────
    always @(posedge clk) begin
        if (!rst_n) pc <= 32'd0;
        else        pc <= next_pc;
    end
endmodule

rtl/rv32i/rv32i_soc.v
// RV32I SoC – core + IMEM (ROM) + DMEM (word-addressed RAM)
// IMEM: 256 words (1 KB), DMEM: 256 words (1 KB)
module rv32i_soc #(
    parameter IMEM_FILE = "prog.hex"
) (
    input clk,
    input rst_n
);
    // ── Instruction memory ──────────────────────────────────
    reg [31:0] imem [0:255];
    initial $readmemh(IMEM_FILE, imem);

    wire [31:0] imem_addr, imem_rdata;
    assign imem_rdata = imem[imem_addr[9:2]];

    // ── Data memory (word-addressed) ────────────────────────
    // Word address = byte_addr >> 2  (all accesses must be word-aligned)
    reg  [31:0] dmem [0:255];
    wire [31:0] dmem_addr, dmem_wdata;
    wire [3:0]  dmem_wmask;
    wire        dmem_wen;
    wire [31:0] dmem_rdata;

    assign dmem_rdata = dmem[dmem_addr[9:2]];

    always @(posedge clk)
        if (dmem_wen) dmem[dmem_addr[9:2]] <= dmem_wdata;

    // ── Core ─────────────────────────────────────────────────
    rv32i_core u_core (
        .clk        (clk),
        .rst_n      (rst_n),
        .imem_addr  (imem_addr),
        .imem_rdata (imem_rdata),
        .dmem_addr  (dmem_addr),
        .dmem_wdata (dmem_wdata),
        .dmem_wmask (dmem_wmask),
        .dmem_wen   (dmem_wen),
        .dmem_rdata (dmem_rdata)
    );
endmodule

rtl/rv32i/tb_rv32i.v
`timescale 1ns/1ps
module tb_rv32i;
    reg clk, rst_n;

    rv32i_soc #(.IMEM_FILE("rtl/rv32i/prog.hex")) dut (.clk(clk), .rst_n(rst_n));

    initial clk = 0;
    always #5 clk = ~clk;

    integer errors = 0;
    integer cycle  = 0;

    task check32;
        input [31:0] got, exp;
        input [255:0] label;
        begin
            if (got !== exp) begin
                $display("FAIL [%0s]: got=%0d exp=%0d", label, got, exp);
                errors = errors + 1;
            end else
                $display("PASS [%0s]: %0d", label, got);
        end
    endtask

    // done: jal x0, done is the last instruction (PC=0x68)
    localparam DONE_PC = 32'h6C;   // done: jal x0, done (28 instr * 4 = 0x70 - 4 = 0x6C)
    localparam TIMEOUT = 5000;

    initial begin
        $dumpfile("sim/rv32i_sim.vcd");
        $dumpvars(0, tb_rv32i);

        rst_n = 0;
        repeat(4) @(posedge clk);
        rst_n = 1;

        while (dut.u_core.pc !== DONE_PC && cycle < TIMEOUT) begin
            @(posedge clk);
            cycle = cycle + 1;
        end

        if (cycle >= TIMEOUT) begin
            $display("TIMEOUT at cycle %0d, PC=0x%h", cycle, dut.u_core.pc);
            errors = errors + 1;
        end else begin
            $display("Halted at PC=0x%h after %0d cycles", dut.u_core.pc, cycle);
        end

        // dmem is word-addressed: dmem[0]=addr0, dmem[1]=addr4, dmem[2]=addr8, dmem[3]=addr12
        check32(dut.dmem[0], 32'd55,  "fib(10)=55 @ dmem[0]");
        check32(dut.dmem[1], 32'd34,  "fib(9)=34  @ dmem[1]");
        check32(dut.dmem[2], 32'd220, "55<<2=220  @ dmem[2]");
        check32(dut.dmem[3], 32'd42,  "jal_test=42@ dmem[3]");

        // x16 should be 0 (jal skipped that addi)
        check32(dut.u_core.u_rf.rf[16], 32'd0, "x16=0 (jal-skipped)");

        if (errors == 0)
            $display("\n=== RV32I SIM PASSED (%0d cycles) ===", cycle);
        else
            $display("\n=== RV32I SIM FAILED (%0d errors) ===", errors);
        $finish;
    end
endmodule

sim/rv32i_sim.vcd
$date
	Thu May 21 05:32:55 2026
$end
$version
	Icarus Verilog
$end
$timescale
	1ps
$end
$scope module tb_rv32i $end
$var parameter 32 ! DONE_PC $end
$var parameter 32 " TIMEOUT $end
$var reg 1 # clk $end
$var reg 1 $ rst_n $end
$var integer 32 % cycle [31:0] $end
$var integer 32 & errors [31:0] $end
$scope module dut $end
$var wire 1 # clk $end
$var wire 32 ' dmem_rdata [31:0] $end
$var wire 32 ( imem_rdata [31:0] $end
$var wire 1 $ rst_n $end
$var wire 32 ) imem_addr [31:0] $end
$var wire 4 * dmem_wmask [3:0] $end
$var wire 1 + dmem_wen $end
$var wire 32 , dmem_wdata [31:0] $end
$var wire 32 - dmem_addr [31:0] $end
$var parameter 144 . IMEM_FILE $end
$scope module u_core $end
$var wire 1 # clk $end
$var wire 32 / dmem_addr [31:0] $end
$var wire 32 0 dmem_rdata [31:0] $end
$var wire 32 1 dmem_wdata [31:0] $end
$var wire 32 2 imem_addr [31:0] $end
$var wire 32 3 imem_rdata [31:0] $end
$var wire 32 4 instr [31:0] $end
$var wire 1 5 is_sra $end
$var wire 1 6 is_sub $end
$var wire 32 7 lw [31:0] $end
$var wire 32 8 rs1v [31:0] $end
$var wire 32 9 rs2v [31:0] $end
$var wire 1 $ rst_n $end
$var wire 5 : rs2 [4:0] $end
$var wire 5 ; rs1 [4:0] $end
$var wire 32 < rf_rdata2 [31:0] $end
$var wire 32 = rf_rdata1 [31:0] $end
$var wire 5 > rd [4:0] $end
$var wire 32 ? pc_plus4 [31:0] $end
$var wire 32 @ pc_jalr [31:0] $end
$var wire 32 A pc_jal [31:0] $end
$var wire 32 B pc_branch [31:0] $end
$var wire 7 C opcode [6:0] $end
$var wire 32 D lhu [31:0] $end
$var wire 32 E lh [31:0] $end
$var wire 32 F lbu [31:0] $end
$var wire 32 G lb [31:0] $end
$var wire 1 H is_r $end
$var wire 1 I is_i $end
$var wire 32 J imm_u [31:0] $end
$var wire 32 K imm_s [31:0] $end
$var wire 32 L imm_j [31:0] $end
$var wire 32 M imm_i [31:0] $end
$var wire 32 N imm_b [31:0] $end
$var wire 7 O funct7 [6:0] $end
$var wire 3 P funct3 [2:0] $end
$var wire 4 Q dmem_wmask [3:0] $end
$var wire 1 + dmem_wen $end
$var wire 1 R br_ltu $end
$var wire 1 S br_lt $end
$var wire 1 T br_eq $end
$var wire 1 U alu_zero $end
$var wire 32 V alu_result [31:0] $end
$var parameter 4 W ALU_ADD $end
$var parameter 4 X ALU_AND $end
$var parameter 4 Y ALU_OR $end
$var parameter 4 Z ALU_PASS $end
$var parameter 4 [ ALU_SLL $end
$var parameter 4 \ ALU_SLT $end
$var parameter 4 ] ALU_SLTU $end
$var parameter 4 ^ ALU_SRA $end
$var parameter 4 _ ALU_SRL $end
$var parameter 4 ` ALU_SUB $end
$var parameter 4 a ALU_XOR $end
$var parameter 7 b OP_ALU $end
$var parameter 7 c OP_ALUI $end
$var parameter 7 d OP_AUIPC $end
$var parameter 7 e OP_BRANCH $end
$var parameter 7 f OP_JAL $end
$var parameter 7 g OP_JALR $end
$var parameter 7 h OP_LOAD $end
$var parameter 7 i OP_LUI $end
$var parameter 7 j OP_STORE $end
$var reg 32 k alu_a [31:0] $end
$var reg 32 l alu_b [31:0] $end
$var reg 4 m alu_op [3:0] $end
$var reg 32 n load_data [31:0] $end
$var reg 32 o next_pc [31:0] $end
$var reg 32 p pc [31:0] $end
$var reg 32 q rf_wdata [31:0] $end
$var reg 1 r rf_wen $end
$var reg 1 s taken $end
$scope module u_alu $end
$var wire 32 t a [31:0] $end
$var wire 32 u b [31:0] $end
$var wire 4 v op [3:0] $end
$var wire 1 U zero $end
$var parameter 4 w ADD $end
$var parameter 4 x AND $end
$var parameter 4 y OR $end
$var parameter 4 z PASS $end
$var parameter 4 { SLL $end
$var parameter 4 | SLT $end
$var parameter 4 } SLTU $end
$var parameter 4 ~ SRA $end
$var parameter 4 !" SRL $end
$var parameter 4 "" SUB $end
$var parameter 4 #" XOR $end
$var reg 32 $" result [31:0] $end
$upscope $end
$scope module u_rf $end
$var wire 1 # clk $end
$var wire 5 %" rd [4:0] $end
$var wire 5 &" rs1 [4:0] $end
$var wire 5 '" rs2 [4:0] $end
$var wire 32 (" wdata [31:0] $end
$var wire 1 r wen $end
$var wire 32 )" rdata2 [31:0] $end
$var wire 32 *" rdata1 [31:0] $end
$upscope $end
$upscope $end
$upscope $end
$scope task check32 $end
$var reg 32 +" exp [31:0] $end
$var reg 32 ," got [31:0] $end
$var reg 256 -" label [255:0] $end
$upscope $end
$upscope $end
$enddefinitions $end
$comment Show the parameter values. $end
$dumpall
b101 #"
b1 ""
b110 !"
b111 ~
b100 }
b11 |
b10 {
b1010 z
b1000 y
b1001 x
b0 w
b100011 j
b110111 i
b11 h
b1100111 g
b1101111 f
b1100011 e
b10111 d
b10011 c
b110011 b
b101 a
b1 `
b110 _
b111 ^
b100 ]
b11 \
b10 [
b1010 Z
b1000 Y
b1001 X
b0 W
b11100100111010001101100001011110111001001110110001100110011001001101001001011110111000001110010011011110110011100101110011010000110010101111000 .
b1001110001000 "
b1101100 !
$end
#0
$dumpvars
bx -"
bx ,"
bx +"
bx *"
bx )"
bx ("
bx '"
bx &"
bx %"
bx $"
b0 v
bx u
bx t
xs
xr
bx q
bx p
bx o
bx n
b0 m
bx l
bx k
bx V
xU
xT
xS
xR
bx Q
bx P
bx O
bx0 N
bx M
bx0 L
bx K
bx000000000000 J
xI
xH
bx G
b0xxxxxxxx F
bx E
b0xxxxxxxxxxxxxxxx D
bx C
bx B
bx A
bx0 @
bx ?
bx >
bx =
bx <
bx ;
bx :
bx 9
bx 8
bx 7
x6
x5
bx 4
bx 3
bx 2
bx 1
bx 0
bx /
bx -
bx ,
x+
bx *
bx )
bx (
bx '
b0 &
b0 %
0$
0#
$end
#5000
b0 @
1U
b0 -
b0 /
b0 V
b0 $"
b0 k
b0 t
06
b0 *
b0 Q
05
1s
1T
0S
0R
b0 8
b0 =
b0 *"
b0 ,
b0 1
b0 9
b0 <
b0 )"
b0 m
b0 v
b0 l
b0 u
0H
1I
0+
b10011 C
b1 >
b1 %"
b0 P
b0 ;
b0 &"
b0 :
b0 '"
b0 O
b0 M
b1 K
b100000000000 B
b100000000000 N
b0 J
b0 A
b0 L
b100 o
b0 q
b0 ("
1r
b10010011 4
b10010011 (
b10010011 3
b100 ?
b0 )
b0 2
b0 p
1#
#10000
0#
#15000
1#
#20000
0#
#25000
1#
#30000
0#
#35000
1$
1#
#40000
0#
#45000
b1 q
b1 ("
0U
b1 -
b1 /
b1 V
b1 $"
b1 l
b1 u
b10 >
b10 %"
b1 :
b1 '"
b1 M
b10 K
b10 N
b100000000000000000000 J
b100000000000 L
1r
b1000 o
b100000000000100010011 4
b100000000000100010011 (
b100000000000100010011 3
b1000 ?
b110 B
b100000000100 A
b100 )
b100 2
b100 p
b1 %
1#
#50000
0#
#55000
b1000 @
xs
b1001 -
b1001 /
b1001 V
b1001 $"
bx ,
bx 1
xT
xS
xR
bx 9
bx <
bx )"
b1001 l
b1001 u
b11 >
b11 %"
b1001 :
b1001 '"
b1001 M
b11 K
b100000000010 N
b100100000000000000000000 J
b100000001000 L
b1001 q
b1001 ("
1r
b1100 o
b100100000000000110010011 4
b100100000000000110010011 (
b100100000000000110010011 3
b1100 ?
b100000001010 B
b100000010000 A
b1000 )
b1000 2
b1000 p
b10 %
1#
#60000
0#
#65000
b0 @
0s
0U
b1 -
b1 /
b1 V
b1 $"
b1 ,
b1 1
0T
1S
1R
b1 9
b1 <
b1 )"
b1 l
b1 u
1H
0I
b110011 C
b100 >
b100 %"
b1 ;
b1 &"
b10 :
b10 '"
b10 M
b100 K
b100 N
b1000001000000000000000 J
b1000000000000010 L
b1 q
b1 ("
1r
b10000 o
b1000001000001000110011 4
b1000001000001000110011 (
b1000001000001000110011 3
b10000 ?
b10000 B
b1000000000001110 A
b1100 )
b1100 2
b1100 p
b11 %
1#
#70000
0#
#75000
b1 k
b1 t
0U
b1 -
b1 /
b1 V
b1 $"
b1 8
b1 =
b1 *"
b0 ,
b0 1
0T
0S
0R
b0 9
b0 <
b0 )"
b0 l
b0 u
0H
1I
b10011 C
b1 >
b1 %"
b10 ;
b10 &"
b0 :
b0 '"
b0 M
b1 K
b100000000000 N
b10000000000000000 J
b10000000000000000 L
b1 q
b1 ("
1r
b10100 o
b10000000010010011 4
b10000000010010011 (
b10000000010010011 3
b10100 ?
b100000010000 B
b10000000000010000 A
b10000 )
b10000 2
b10000 p
b100 %
1#
#80000
0#
#85000
b10 >
b10 %"
b100 ;
b100 &"
b10 K
b10 N
b100000000000000000 J
b100000000000000000 L
b1 q
b1 ("
1r
b11000 o
b100000000100010011 4
b100000000100010011 (
b100000000100010011 3
b11000 ?
b10110 B
b100000000000010100 A
b10100 )
b10100 2
b10100 p
b101 %
1#
#90000
0#
#95000
b1000 @
b1001 k
b1001 t
xs
0U
b1000 -
b1000 /
b1000 V
b1000 $"
b1001 8
b1001 =
b1001 *"
bx ,
bx 1
xT
xS
xR
bx 9
bx <
bx )"
b11111111111111111111111111111111 l
b11111111111111111111111111111111 u
b11 >
b11 %"
b11 ;
b11 &"
b11111 :
b11111 '"
b1111111 O
b11111111111111111111111111111111 M
b11111111111111111111111111100011 K
b11111111111111111111111111100010 N
b11111111111100011000000000000000 J
b11111111111100011000111111111110 L
b1000 q
b1000 ("
1r
b11100 o
b11111111111100011000000110010011 4
b11111111111100011000000110010011 (
b11111111111100011000000110010011 3
b11100 ?
b11111111111111111111111111111010 B
b11111111111100011001000000010110 A
b11000 )
b11000 2
b11000 p
b110 %
1#
#100000
0#
#105000
b11111111111111111111111111101000 @
b11111111111111111111111111101000 -
b11111111111111111111111111101000 /
b11111111111111111111111111101000 V
b11111111111111111111111111101000 $"
1s
b0 ,
b0 1
0T
0S
0R
b0 9
b0 <
b0 )"
b0 m
b0 v
b11111111111111111111111111100000 l
b11111111111111111111111111100000 u
b1000 k
b1000 t
0I
b1100011 C
b10001 >
b10001 %"
b1 P
b0 :
b0 '"
b11111111111111111111111111100000 M
b11111111111111111111111111110001 K
b11111111111111111111111111110000 N
b11111110000000011001000000000000 J
b11111111111100011001011111100000 L
b1000 8
b1000 =
b1000 *"
b0 q
b0 ("
0r
b1100 o
b11111110000000011001100011100011 4
b11111110000000011001100011100011 (
b11111110000000011001100011100011 3
b100000 ?
b1100 B
b11111111111100011001011111111100 A
b11100 )
b11100 2
b11100 p
b111 %
1#
#110000
0#
#115000
b10 @
b1 k
b1 t
b10 -
b10 /
b10 V
b10 $"
b10 q
b10 ("
1r
1T
b1 8
b1 =
b1 *"
b1 ,
b1 1
b1 9
b1 <
b1 )"
b1 l
b1 u
1H
b110011 C
b100 >
b100 %"
b0 P
b1 ;
b1 &"
b10 :
b10 '"
b0 O
b10 M
b100 K
b100 N
b1000001000000000000000 J
b1000000000000010 L
b0 m
b0 v
b10000 o
b1000001000001000110011 4
b1000001000001000110011 (
b1000001000001000110011 3
b10000 ?
b10000 B
b1000000000001110 A
b1100 )
b1100 2
b1100 p
b1000 %
1#
#120000
0#
#125000
b0 @
0s
b1 -
b1 /
b1 V
b1 $"
b0 ,
b0 1
0T
b0 9
b0 <
b0 )"
b0 l
b0 u
0H
1I
b10011 C
b1 >
b1 %"
b10 ;
b10 &"
b0 :
b0 '"
b0 M
b1 K
b100000000000 N
b10000000000000000 J
b10000000000000000 L
b1 q
b1 ("
1r
b10100 o
b10000000010010011 4
b10000000010010011 (
b10000000010010011 3
b10100 ?
b100000010000 B
b10000000000010000 A
b10000 )
b10000 2
b10000 p
b1001 %
1#
#130000
0#
#135000
b10 @
b10 -
b10 /
b10 V
b10 $"
b10 k
b10 t
b10 8
b10 =
b10 *"
b10 >
b10 %"
b100 ;
b100 &"
b10 K
b10 N
b100000000000000000 J
b100000000000000000 L
b10 q
b10 ("
1r
b11000 o
b100000000100010011 4
b100000000100010011 (
b100000000100010011 3
b11000 ?
b10110 B
b100000000000010100 A
b10100 )
b10100 2
b10100 p
b1010 %
1#
#140000
0#
#145000
b110 @
b1000 k
b1000 t
xs
b111 -
b111 /
b111 V
b111 $"
b1000 8
b1000 =
b1000 *"
bx ,
bx 1
xT
xS
xR
bx 9
bx <
bx )"
b11111111111111111111111111111111 l
b11111111111111111111111111111111 u
b11 >
b11 %"
b11 ;
b11 &"
b11111 :
b11111 '"
b1111111 O
b11111111111111111111111111111111 M
b11111111111111111111111111100011 K
b11111111111111111111111111100010 N
b11111111111100011000000000000000 J
b11111111111100011000111111111110 L
b111 q
b111 ("
1r
b11100 o
b11111111111100011000000110010011 4
b11111111111100011000000110010011 (
b11111111111100011000000110010011 3
b11100 ?
b11111111111111111111111111111010 B
b11111111111100011001000000010110 A
b11000 )
b11000 2
b11000 p
b1011 %
1#
#150000
0#
#155000
b11111111111111111111111111100110 @
1s
b0 ,
b0 1
0T
0S
0R
b0 9
b0 <
b0 )"
b0 m
b0 v
b11111111111111111111111111100000 l
b11111111111111111111111111100000 u
b11111111111111111111111111100111 -
b11111111111111111111111111100111 /
b11111111111111111111111111100111 V
b11111111111111111111111111100111 $"
0I
b1100011 C
b10001 >
b10001 %"
b1 P
b0 :
b0 '"
b11111111111111111111111111100000 M
b11111111111111111111111111110001 K
b11111111111111111111111111110000 N
b11111110000000011001000000000000 J
b11111111111100011001011111100000 L
b111 k
b111 t
b0 q
b0 ("
0r
b1100 o
b11111110000000011001100011100011 4
b11111110000000011001100011100011 (
b11111110000000011001100011100011 3
b111 8
b111 =
b111 *"
b100000 ?
b1100 B
b11111111111100011001011111111100 A
b11100 )
b11100 2
b11100 p
b1100 %
1#
#160000
0#
#165000
b10 @
b1 k
b1 t
b11 -
b11 /
b11 V
b11 $"
b11 q
b11 ("
1r
0s
1S
1R
b1 8
b1 =
b1 *"
b10 ,
b10 1
b10 9
b10 <
b10 )"
b10 l
b10 u
1H
b110011 C
b100 >
b100 %"
b0 P
b1 ;
b1 &"
b10 :
b10 '"
b0 O
b10 M
b100 K
b100 N
b1000001000000000000000 J
b1000000000000010 L
b0 m
b0 v
b10000 o
b1000001000001000110011 4
b1000001000001000110011 (
b1000001000001000110011 3
b10000 ?
b10000 B
b1000000000001110 A
b1100 )
b1100 2
b1100 p
b1101 %
1#
#170000
0#
#175000
b10 @
b10 k
b10 t
b10 -
b10 /
b10 V
b10 $"
b10 8
b10 =
b10 *"
b0 ,
b0 1
0S
0R
b0 9
b0 <
b0 )"
b0 l
b0 u
0H
1I
b10011 C
b1 >
b1 %"
b10 ;
b10 &"
b0 :
b0 '"
b0 M
b1 K
b100000000000 N
b10000000000000000 J
b10000000000000000 L
b10 q
b10 ("
1r
b10100 o
b10000000010010011 4
b10000000010010011 (
b10000000010010011 3
b10100 ?
b100000010000 B
b10000000000010000 A
b10000 )
b10000 2
b10000 p
b1110 %
1#
#180000
0#
#185000
b11 -
b11 /
b11 V
b11 $"
b11 k
b11 t
b11 8
b11 =
b11 *"
b10 >
b10 %"
b100 ;
b100 &"
b10 K
b10 N
b100000000000000000 J
b100000000000000000 L
b11 q
b11 ("
1r
b11000 o
b100000000100010011 4
b100000000100010011 (
b100000000100010011 3
b11000 ?
b10110 B
b100000000000010100 A
b10100 )
b10100 2
b10100 p
b1111 %
1#
#190000
0#
#195000
b110 @
b111 k
b111 t
xs
b110 -
b110 /
b110 V
b110 $"
b111 8
b111 =
b111 *"
bx ,
bx 1
xT
xS
xR
bx 9
bx <
bx )"
b11111111111111111111111111111111 l
b11111111111111111111111111111111 u
b11 >
b11 %"
b11 ;
b11 &"
b11111 :
b11111 '"
b1111111 O
b11111111111111111111111111111111 M
b11111111111111111111111111100011 K
b11111111111111111111111111100010 N
b11111111111100011000000000000000 J
b11111111111100011000111111111110 L
b110 q
b110 ("
1r
b11100 o
b11111111111100011000000110010011 4
b11111111111100011000000110010011 (
b11111111111100011000000110010011 3
b11100 ?
b11111111111111111111111111111010 B
b11111111111100011001000000010110 A
b11000 )
b11000 2
b11000 p
b10000 %
1#
#200000
0#
#205000
b11111111111111111111111111100110 @
b11111111111111111111111111100110 -
b11111111111111111111111111100110 /
b11111111111111111111111111100110 V
b11111111111111111111111111100110 $"
1s
b0 ,
b0 1
0T
0S
0R
b0 9
b0 <
b0 )"
b0 m
b0 v
b11111111111111111111111111100000 l
b11111111111111111111111111100000 u
b110 k
b110 t
0I
b1100011 C
b10001 >
b10001 %"
b1 P
b0 :
b0 '"
b11111111111111111111111111100000 M
b11111111111111111111111111110001 K
b11111111111111111111111111110000 N
b11111110000000011001000000000000 J
b11111111111100011001011111100000 L
b110 8
b110 =
b110 *"
b0 q
b0 ("
0r
b1100 o
b11111110000000011001100011100011 4
b11111110000000011001100011100011 (
b11111110000000011001100011100011 3
b100000 ?
b1100 B
b11111111111100011001011111111100 A
b11100 )
b11100 2
b11100 p
b10001 %
1#
#210000
0#
#215000
b100 @
b10 k
b10 t
b101 -
b101 /
b101 V
b101 $"
b101 q
b101 ("
1r
0s
1S
1R
b10 8
b10 =
b10 *"
b11 ,
b11 1
b11 9
b11 <
b11 )"
b11 l
b11 u
1H
b110011 C
b100 >
b100 %"
b0 P
b1 ;
b1 &"
b10 :
b10 '"
b0 O
b10 M
b100 K
b100 N
b1000001000000000000000 J
b1000000000000010 L
b0 m
b0 v
b10000 o
b1000001000001000110011 4
b1000001000001000110011 (
b1000001000001000110011 3
b10000 ?
b10000 B
b1000000000001110 A
b1100 )
b1100 2
b1100 p
b10010 %
1#
#220000
0#
